sbo_create/__init__.py
sbo_create/__metadata__.py
sbo_create/main.py
sbo_create/templates.py
sbo_create-2.0.8.dist-info/entry_points.txt
sbo_create-2.0.8.dist-info/WHEEL
sbo_create-2.0.8.dist-info/METADATA
sbo_create-2.0.8.dist-info/RECORD
