Metadata-Version: 2.1
Name: sbo-create
Version: 2.0.8
Summary: SBo tool for creating SlackBuilds.
Keywords: sbo,templates,slackbuild
Author-email: Dimitris Zlatanidis <dslackw@gmail.com>
Maintainer-email: Dimitris Zlatanidis <dslackw@gmail.com>
Requires-Python: >=3.9
Classifier: Development Status :: 5 - Production/Stable
Classifier: License :: OSI Approved :: MIT License
Classifier: Operating System :: Unix
Classifier: Programming Language :: Python
Classifier: Programming Language :: Python :: 3
Requires-Dist: pythondialog>=3.5.3
Project-URL: Changelog, https://gitlab.com/dslackw/sbo-create/-/blob/main/ChangeLog.txt
Project-URL: Documentation, https://dslackw.gitlab.io/sbo-create/
Project-URL: Homepage, https://dslackw.gitlab.io/sbo-create/
Project-URL: Repository, https://gitlab.com/dslackw/sbo-create.git
